experimaestro/__init__.py
experimaestro/__main__.py
experimaestro/annotations.py
experimaestro/checkers.py
experimaestro/cli/__init__.py
experimaestro/cli/filter.py
experimaestro/cli/jobs.py
experimaestro/click.py
experimaestro/commandline.py
experimaestro/compat.py
experimaestro/connectors/__init__.py
experimaestro/connectors/local.py
experimaestro/connectors/ssh.py
experimaestro/core/__init__.py
experimaestro/core/arguments.py
experimaestro/core/callbacks.py
experimaestro/core/context.py
experimaestro/core/identifier.py
experimaestro/core/objects/__init__.py
experimaestro/core/objects/config.py
experimaestro/core/objects/config_utils.py
experimaestro/core/objects/config_walk.py
experimaestro/core/objects.pyi
experimaestro/core/serialization.py
experimaestro/core/serializers.py
experimaestro/core/types.py
experimaestro/core/utils.py
experimaestro/exceptions.py
experimaestro/experiments/__init__.py
experimaestro/experiments/cli.py
experimaestro/experiments/configuration.py
experimaestro/generators.py
experimaestro/huggingface.py
experimaestro/ipc.py
experimaestro/launcherfinder/__init__.py
experimaestro/launcherfinder/base.py
experimaestro/launcherfinder/parser.py
experimaestro/launcherfinder/registry.py
experimaestro/launcherfinder/specs.py
experimaestro/launchers/__init__.py
experimaestro/launchers/direct.py
experimaestro/launchers/oar.py
experimaestro/launchers/slurm/__init__.py
experimaestro/launchers/slurm/base.py
experimaestro/locking.py
experimaestro/mkdocs/__init__.py
experimaestro/mkdocs/annotations.py
experimaestro/mkdocs/base.py
experimaestro/mkdocs/metaloader.py
experimaestro/mkdocs/style.css
experimaestro/mypy.py
experimaestro/notifications.py
experimaestro/py.typed
experimaestro/rpyc.py
experimaestro/run.py
experimaestro/scheduler/__init__.py
experimaestro/scheduler/base.py
experimaestro/scheduler/dependencies.py
experimaestro/scheduler/dynamic_outputs.py
experimaestro/scheduler/services.py
experimaestro/scheduler/state.py
experimaestro-1.15.1.dist-info/METADATA
experimaestro-1.15.1.dist-info/WHEEL
experimaestro-1.15.1.dist-info/entry_points.txt
experimaestro-1.15.1.dist-info/licenses/LICENSE
experimaestro-1.15.1.dist-info/RECORD
