Metadata-Version: 2.4
Name: experimaestro
Version: 1.15.1
Summary: "Experimaestro is a computer science experiment manager"
License: GPL-3
License-File: LICENSE
Keywords: experiment manager
Author: Benjamin Piwowarski
Author-email: benjamin@piwowarski.fr
Requires-Python: >=3.10
Classifier: Development Status :: 4 - Beta
Classifier: Intended Audience :: Science/Research
Classifier: License :: OSI Approved :: GNU General Public License v3 (GPLv3)
Classifier: Operating System :: OS Independent
Classifier: Programming Language :: Python
Classifier: Programming Language :: Python :: 3
Classifier: Topic :: Software Development :: Libraries :: Python Modules
Requires-Dist: arpeggio (>=2,<3)
Requires-Dist: attrs (>=23.1.0,<24)
Requires-Dist: click (>=8)
Requires-Dist: decorator (>=5,<6)
Requires-Dist: docstring-parser (>=0.15,<1)
Requires-Dist: fasteners (>=0.19,<1)
Requires-Dist: flask (>=2.3)
Requires-Dist: flask-socketio (>=5.3)
Requires-Dist: gevent (>=25)
Requires-Dist: gevent-websocket (>=0.10)
Requires-Dist: huggingface-hub (>0.17)
Requires-Dist: humanfriendly (>=10)
Requires-Dist: marshmallow (>=3.20,<4)
Requires-Dist: mkdocs (>=1.5,<2)
Requires-Dist: omegaconf (>=2.3,<3)
Requires-Dist: psutil (>=7,<8)
Requires-Dist: pyparsing (>=3.1,<4)
Requires-Dist: pytools (>=2023.1.1,<2024)
Requires-Dist: pyyaml (>=6.0.1,<7)
Requires-Dist: requests (>=2.31,<3)
Requires-Dist: rpyc (>=5,<7)
Requires-Dist: sortedcontainers (>=2.4,<3)
Requires-Dist: termcolor (>=2.3,<3)
Requires-Dist: tqdm (>=4.66.1,<5)
Requires-Dist: typing-extensions (>=4.2) ; python_version < "3.12"
Requires-Dist: watchdog (>=2)
